Workbook
Name tot_table: 'product data entry'!$A$1:$H$51

Sheet summarry
A1: Order_id | B1: Product name | C1: Customer_Reviews | D1: Quality
A2: 19051 | B2: mobile | C2: 5 | D2: =IF(C1>4,"High","Medium") -> High
A3: 19052 | B3: laptop | C3: 5 | D3: =IF(C2>4,"High","Medium") -> High
A4: 19053 | B4: headphones | C4: 4.8 | D4: =IF(C3>4,"High","Medium") -> High
A5: 19054 | B5: smartwatch | C5: 4.5 | D5: =IF(C4>4,"High","Medium") -> High | I5: High | J5: >4
A6: 19055 | B6: keyboard | C6: 5 | D6: =IF(C5>4,"High","Medium") -> High | I6: Medium | J6: >=3 | N6: 50
A7: 19056 | B7: pendrive | C7: 3 | D7: =IF(C6>4,"High","Medium") -> High | I7: Low | J7: <3 | N7: 15
A8: 19057 | B8: mouse | C8: 3 | D8: =IF(C7>4,"High","Medium") -> Medium
A9: 19058 | B9: mobile | C9: 4 | D9: =IF(C8>4,"High","Medium") -> Medium
A10: 19059 | B10: laptop | C10: 5 | D10: =IF(C9>4,"High","Medium") -> Medium
A11: 19060 | B11: headphones | C11: 5 | D11: =IF(C10>4,"High","Medium") -> High
A12: 19061 | B12: smartwatch | C12: 4 | D12: =IF(C11>4,"High","Medium") -> High | J12: percentage | K12: =N6-N7 -> 35
A13: 19062 | B13: keyboard | C13: 4.5 | D13: =IF(C12>4,"High","Medium") -> Medium
A14: 19063 | B14: pendrive | C14: 4 | D14: =IF(C13>4,"High","Medium") -> High
A15: 19064 | B15: mouse | C15: 3.8 | D15: =IF(C14>4,"High","Medium") -> Medium
A16: 19065 | B16: mobile | C16: 4.9 | D16: =IF(C15>4,"High","Medium") -> Medium
A17: 19066 | B17: laptop
A18: 19067 | B18: headphones
A19: 19068 | B19: smartwatch
A20: 19069 | B20: keyboard
A21: 19070 | B21: pendrive
A22: 19071 | B22: mouse
A23: 19072 | B23: mobile
A24: 19073 | B24: laptop
A25: 19074 | B25: headphones
A26: 19075 | B26: smartwatch
A27: 19076 | B27: keyboard
A28: 19077 | B28: pendrive
... A51: 19100 | B51: mobile

Sheet product data entry
A1: Order_id | B1: Product name | C1: Date | D1: Quantity | E1: Price | F1: Total amount | G1: Category | H1: product model | I1: Target sales | J1: Month name
A2: 19051 | B2: mobile | C2: 45974 | D2: 3 | E2: 20000 | F2: =SUM(E2*D2) -> 60000 | G2: =VLOOKUP(Table6[[#This Row],[Product name]],Table1[],2,FALSE) -> electronics | H2: =VLOOKUP(Table6[[#This Row],[Product name]],'product details'!$A$2:$C$9,3,0) -> iphone | I2: 150000 | J2: =TEXT(Table6[[#This Row],[Date]],"mmm") -> Nov
A3: 19052 | B3: laptop | C3: 45975 | D3: 6 | E3: 89000 | F3: =SUM(E3*D3) -> 534000 | G3: =VLOOKUP(Table6[[#This Row],[Product name]],Table1[],2,FALSE) -> electronics | H3: =VLOOKUP(Table6[[#This Row],[Product name]],'product details'!$A$2:$C$9,3,0) -> dell | I3: 150000 | J3: =TEXT(Table6[[#This Row],[Date]],"mmm") -> Nov
A4: 19053 | B4: headphones | C4: 45976 | D4: 2 | E4: 6000 | F4: =SUM(E4*D4) -> 12000 | G4: =VLOOKUP(Table6[[#This Row],[Product name]],Table1[],2,FALSE) -> accessories | H4: =VLOOKUP(Table6[[#This Row],[Product name]],'product details'!$A$2:$C$9,3,0) -> realme | I4: 150000 | J4: =TEXT(Table6[[#This Row],[Date]],"mmm") -> Nov
A5: 19054 | B5: smartwatch | C5: 45977 | D5: 8 | E5: 56000 | F5: =SUM(E5*D5) -> 448000 | G5: =VLOOKUP(Table6[[#This Row],[Product name]],Table1[],2,FALSE) -> electronics | H5: =VLOOKUP(Table6[[#This Row],[Product name]],'product details'!$A$2:$C$9,3,0) -> wearfit | I5: 150000 | J5: =TEXT(Table6[[#This Row],[Date]],"mmm") -> Nov
A6: 19055 | B6: keyboard | C6: 45978 | D6: 3 | E6: 45600 | F6: =SUM(E6*D6) -> 136800 | G6: =VLOOKUP(Table6[[#This Row],[Product name]],Table1[],2,FALSE) -> accessories | H6: =VLOOKUP(Table6[[#This Row],[Product name]],'product details'!$A$2:$C$9,3,0) -> hp | I6: 150000 | J6: =TEXT(Table6[[#This Row],[Date]],"mmm") -> Nov
A7: 19056 | B7: pendrive | C7: 45979 | D7: 2 | E7: 67000 | F7: =SUM(E7*D7) -> 134000 | G7: =VLOOKUP(Table6[[#This Row],[Product name]],Table1[],2,FALSE) -> storage | H7: =VLOOKUP(Table6[[#This Row],[Product name]],'product details'!$A$2:$C$9,3,0) -> 70gb | I7: 150000 | J7: =TEXT(Table6[[#This Row],[Date]],"mmm") -> Nov
A8: 19057 | B8: mouse | C8: 45980 | D8: 5 | E8: 8900 | F8: =SUM(E8*D8) -> 44500 | G8: =VLOOKUP(Table6[[#This Row],[Product name]],Table1[],2,FALSE) -> accessories | H8: =VLOOKUP(Table6[[#This Row],[Product name]],'product details'!$A$2:$C$9,3,0) -> samsung | I8: 150000 | J8: =TEXT(Table6[[#This Row],[Date]],"mmm") -> Nov
A9: 19058 | B9: mobile | C9: 45981 | D9: 6 | E9: 23000 | F9: =SUM(E9*D9) -> 138000 | G9: =VLOOKUP(Table6[[#This Row],[Product name]],Table1[],2,FALSE) -> electronics | H9: =VLOOKUP(Table6[[#This Row],[Product name]],'product details'!$A$2:$C$9,3,0) -> iphone | I9: 150000 | J9: =TEXT(Table6[[#This Row],[Date]],"mmm") -> Nov
A10: 19059 | B10: laptop | C10: 45982 | D10: 4 | E10: 67000 | F10: =SUM(E10*D10) -> 268000 | G10: =VLOOKUP(Table6[[#This Row],[Product name]],Table1[],2,FALSE) -> electronics | H10: =VLOOKUP(Table6[[#This Row],[Product name]],'product details'!$A$2:$C$9,3,0) -> dell | I10: 150000 | J10: =TEXT(Table6[[#This Row],[Date]],"mmm") -> Nov
A11: 19060 | B11: headphones | C11: 45983 | D11: 3 | E11: 45000 | F11: =SUM(E11*D11) -> 135000 | G11: =VLOOKUP(Table6[[#This Row],[Product name]],Table1[],2,FALSE) -> accessories | H11: =VLOOKUP(Table6[[#This Row],[Product name]],'product details'!$A$2:$C$9,3,0) -> realme | I11: 150000 | J11: =TEXT(Table6[[#This Row],[Date]],"mmm") -> Nov
A12: 19061 | B12: smartwatch | C12: 45984 | D12: 2 | E12: 34000 | F12: =SUM(E12*D12) -> 68000 | G12: =VLOOKUP(Table6[[#This Row],[Product name]],Table1[],2,FALSE) -> electronics | H12: =VLOOKUP(Table6[[#This Row],[Product name]],'product details'!$A$2:$C$9,3,0) -> wearfit | I12: 150000 | J12: =TEXT(Table6[[#This Row],[Date]],"mmm") -> Nov
A13: 19062 | B13: keyboard | C13: 45985 | D13: 3 | E13: 23900 | F13: =SUM(E13*D13) -> 71700 | G13: =VLOOKUP(Table6[[#This Row],[Product name]],Table1[],2,FALSE) -> accessories | H13: =VLOOKUP(Table6[[#This Row],[Product name]],'product details'!$A$2:$C$9,3,0) -> hp | I13: 150000 | J13: =TEXT(Table6[[#This Row],[Date]],"mmm") -> Nov
... A16: 19065 | B16: mobile | C16: 45988 | D16: 2 | E16: 22000 | F16: =SUM(E16*D16) -> 44000 | G16: =VLOOKUP(Table6[[#This Row],[Product name]],Table1[],2,FALSE) -> electronics | H16: =VLOOKUP(Table6[[#This Row],[Product name]],'product details'!$A$2:$C$9,3,0) -> iphone | I16: 150000 | J16: =TEXT(Table6[[#This Row],[Date]],"mmm") -> Nov
A17: 19066 | B17: laptop | C17: 45989 | D17: 6 | G17: =VLOOKUP(Table6[[#This Row],[Product name]],Table1[],2,FALSE) -> electronics | H17: =VLOOKUP(Table6[[#This Row],[Product name]],'product details'!$A$2:$C$9,3,0) -> dell | I17: 150000 | J17: =TEXT(Table6[[#This Row],[Date]],"mmm") -> Nov
A18: 19067 | B18: headphones | C18: 45990 | D18: 4 | G18: =VLOOKUP(Table6[[#This Row],[Product name]],Table1[],2,FALSE) -> accessories | H18: =VLOOKUP(Table6[[#This Row],[Product name]],'product details'!$A$2:$C$9,3,0) -> realme | I18: 150000 | J18: =TEXT(Table6[[#This Row],[Date]],"mmm") -> Nov
A19: 19068 | B19: smartwatch | C19: 45991 | D19: 6 | G19: =VLOOKUP(Table6[[#This Row],[Product name]],Table1[],2,FALSE) -> electronics | H19: =VLOOKUP(Table6[[#This Row],[Product name]],'product details'!$A$2:$C$9,3,0) -> wearfit | I19: 150000 | J19: =TEXT(Table6[[#This Row],[Date]],"mmm") -> Nov
A20: 19069 | B20: keyboard | C20: 45992 | D20: 4 | G20: =VLOOKUP(Table6[[#This Row],[Product name]],Table1[],2,FALSE) -> accessories | H20: =VLOOKUP(Table6[[#This Row],[Product name]],'product details'!$A$2:$C$9,3,0) -> hp | I20: 150000 | J20: =TEXT(Table6[[#This Row],[Date]],"mmm") -> Dec
A21: 19070 | B21: pendrive | C21: 45993 | D21: 2 | G21: =VLOOKUP(Table6[[#This Row],[Product name]],Table1[],2,FALSE) -> storage | H21: =VLOOKUP(Table6[[#This Row],[Product name]],'product details'!$A$2:$C$9,3,0) -> 70gb | I21: 150000 | J21: =TEXT(Table6[[#This Row],[Date]],"mmm") -> Dec
A22: 19071 | B22: mouse | C22: 45994 | D22: 3 | G22: =VLOOKUP(Table6[[#This Row],[Product name]],Table1[],2,FALSE) -> accessories | H22: =VLOOKUP(Table6[[#This Row],[Product name]],'product details'!$A$2:$C$9,3,0) -> samsung | I22: 150000 | J22: =TEXT(Table6[[#This Row],[Date]],"mmm") -> Dec
A23: 19072 | B23: mobile | C23: 45995 | D23: 4 | G23: =VLOOKUP(Table6[[#This Row],[Product name]],Table1[],2,FALSE) -> electronics | H23: =VLOOKUP(Table6[[#This Row],[Product name]],'product details'!$A$2:$C$9,3,0) -> iphone | I23: 150000 | J23: =TEXT(Table6[[#This Row],[Date]],"mmm") -> Dec
A24: 19073 | B24: laptop | C24: 45996 | D24: 5 | G24: =VLOOKUP(Table6[[#This Row],[Product name]],Table1[],2,FALSE) -> electronics | H24: =VLOOKUP(Table6[[#This Row],[Product name]],'product details'!$A$2:$C$9,3,0) -> dell | I24: 150000 | J24: =TEXT(Table6[[#This Row],[Date]],"mmm") -> Dec
A25: 19074 | B25: headphones | C25: 45997 | D25: 2 | G25: =VLOOKUP(Table6[[#This Row],[Product name]],Table1[],2,FALSE) -> accessories | H25: =VLOOKUP(Table6[[#This Row],[Product name]],'product details'!$A$2:$C$9,3,0) -> realme | I25: 150000 | J25: =TEXT(Table6[[#This Row],[Date]],"mmm") -> Dec
A26: 19075 | B26: smartwatch | C26: 45998 | D26: 2 | G26: =VLOOKUP(Table6[[#This Row],[Product name]],Table1[],2,FALSE) -> electronics | H26: =VLOOKUP(Table6[[#This Row],[Product name]],'product details'!$A$2:$C$9,3,0) -> wearfit | I26: 150000 | J26: =TEXT(Table6[[#This Row],[Date]],"mmm") -> Dec
A27: 19076 | B27: keyboard | C27: 45999 | D27: 3 | G27: =VLOOKUP(Table6[[#This Row],[Product name]],Table1[],2,FALSE) -> accessories | H27: =VLOOKUP(Table6[[#This Row],[Product name]],'product details'!$A$2:$C$9,3,0) -> hp | I27: 150000 | J27: =TEXT(Table6[[#This Row],[Date]],"mmm") -> Dec
A28: 19077 | B28: pendrive | C28: 46000 | D28: 4 | G28: =VLOOKUP(Table6[[#This Row],[Product name]],Table1[],2,FALSE) -> storage | H28: =VLOOKUP(Table6[[#This Row],[Product name]],'product details'!$A$2:$C$9,3,0) -> 70gb | I28: 150000 | J28: =TEXT(Table6[[#This Row],[Date]],"mmm") -> Dec
... A51: 19100 | B51: mobile | C51: 46023 | D51: 8 | G51: =VLOOKUP(Table6[[#This Row],[Product name]],Table1[],2,FALSE) -> electronics | H51: =VLOOKUP(Table6[[#This Row],[Product name]],'product details'!$A$2:$C$9,3,0) -> iphone | I51: 150000 | J51: =TEXT(Table6[[#This Row],[Date]],"mmm") -> Jan

Sheet dashboard

Sheet product details
B1: Reference table
A2: Product name | B2: category | C2: produt model | K2: {=_xlfn.UNIQUE('product data entry'!J:J)} -> Month name | L2: Sales
A3: laptop | B3: electronics | C3: dell | K3: Nov | L3: =SUMIF(Table6[Month name],'product details'!K3,'product data entry'!$F:$F) -> 2135500
A4: headphones | B4: accessories | C4: realme | K4: Dec | L4: =SUMIF(Table6[Month name],'product details'!K4,'product data entry'!$F:$F) -> 0
A5: keyboard | B5: accessories | C5: hp | K5: Jan | L5: =SUMIF(Table6[Month name],'product details'!K5,'product data entry'!$F:$F) -> 0
A6: mobile | B6: electronics | C6: iphone | E6: revenue target table | K6: 0
A7: smartwatch | B7: electronics | C7: wearfit | E7: target revenue per day | F7: 3000
A8: pendrive | B8: storage | C8: 70gb | E8: total target | F8: 150000
A9: mouse | B9: accessories | C9: samsung | E9: total days | F9: 50
E10: Actual revenue per day | F10: 3500
A14: Total revenue
A15: Category | B15: Total amount | I15: product sales
A16: Electronics | B16: =SUMIF(Table1[category],B4,'product data entry'!F2:F16) -> 590500 | I16: product name | J16: sales
A17: accessories | B17: =SUMIF(Table1[category],B5,'product data entry'!F3:F17) -> 598000 | I17: Laptop | J17: =SUMIF(Table6[Product name],'product data entry'!B3,'product data entry'!E2:E16) -> 156000
A18: storage | B18: =SUMIF(Table1[category],B6,'product data entry'!F4:F18) -> 190500 | I18: Headphones | J18: =SUMIF(Table6[Product name],'product data entry'!B4,'product data entry'!E3:E17) -> 90000
I19: Keyboard | J19: =SUMIF(Table6[Product name],'product data entry'!B5,'product data entry'!E4:E18) -> 77000
I20: Mobile | J20: =SUMIF(Table6[Product name],'product data entry'!B6,'product data entry'!E5:E19) -> 45000
I21: Smartwatch | J21: =SUMIF(Table6[Product name],'product data entry'!B7,'product data entry'!E6:E20) -> 45000
I22: pendrive | J22: =SUMIF(Table6[Product name],'product data entry'!B8,'product data entry'!E7:E21) -> 23900
I23: Mouse | J23: =SUMIF(Table6[Product name],'product data entry'!B9,'product data entry'!E8:E22) -> 10400

Sheet Sales block
A1: sales block
A2: Day count | B2: Total available | C2: =COUNT(Table6[Date]) -> 50
B3: elapsed | C3: =COUNT('product data entry'!E2:E16) -> 15
B4: remaining | C4: =C2-C3 -> 35
A5: sales block | B5: actual revenue | C5: =SUM('product data entry'!E2:E16) -> 518900 | G5: deficit>150000 | H5: platinum
B6: deficit | C6: =C5-C7 -> 466400 | G6: deficit<150000 | H6: silver
B7: expected revenue by today | C7: ='product details'!F10*'Sales block'!C3 -> 52500
A9: Daily average | B9: daily average | C9: ='Sales block'!C5/'Sales block'!C3 -> 34593.333
B10: current | C10: ='product details'!F8-'Sales block'!C5/'Sales block'!C4 -> 135174.29
A12: Projections | B12: Revenue I'll complete at this rate | C12: ='product details'!F9*'product details'!F10 -> 175000
A13: Current status | B13: {=_xlfn.IFS(C7-C5>C6,"platinum",C7-C5<C6,"silver")} -> silver | H13: Trading percentage | J13: 0
A17: Trading sales | J17: trading percentage | K17: =summarry!N6-summarry!N7 -> 35
A18: Overall trades | B18: Coverage | C18: =COUNTA('[1]Excel Syllabus Data'!D5:D105)/COUNTA('[1]Excel Syllabus Data'!C5:C105) -> 0.089108911
B19: Trading scale | C19: =(summarry!N6-summarry!N7)/100 -> 0.35
B20: Rank | C20: =IF(K17>30,"silver jubli","Golden jubli") -> silver jubli | J20: rank
J21: >30 | K21: silver jubli
J22: <30 | K22: golden jubli
